[{"id":1,"first_name":"Lacee","last_name":"Grayston","email":"lgrayston0@360.cn","password":"psBhAr5","is_manager":1,"is_sales":0},
{"id":2,"first_name":"Belvia","last_name":"MacTrustam","email":"bmactrustam1@tmall.com","password":"EY1d0FBiDa6","is_manager":0,"is_sales":0},
{"id":3,"first_name":"Koressa","last_name":"Ropert","email":"kropert2@hugedomains.com","password":"CqWRW2B3JU","is_manager":1,"is_sales":1},
{"id":4,"first_name":"Dalt","last_name":"Hunt","email":"dhunt3@t-online.de","password":"rEWyDk","is_manager":1,"is_sales":1},
{"id":5,"first_name":"Brenden","last_name":"Craigg","email":"bcraigg4@cdbaby.com","password":"8hCLjAiG","is_manager":0,"is_sales":1}]